auto_round/__init__.py
auto_round/autoround.py
auto_round/calib_dataset.py
auto_round/sign_sgd.py
auto_round/utils.py
auto_round/version.py
auto_round/export/__init__.py
auto_round/export/export_to_autogptq.py
auto_round/export/register.py
auto_round/export/export_to_itrex/__init__.py
auto_round/export/export_to_itrex/config.py
auto_round/export/export_to_itrex/export.py
auto_round/export/export_to_itrex/model_wrapper.py
auto_round-0.11.dist-info/LICENSE
auto_round-0.11.dist-info/METADATA
auto_round-0.11.dist-info/WHEEL
auto_round-0.11.dist-info/third-party-programs.txt
auto_round-0.11.dist-info/top_level.txt
auto_round-0.11.dist-info/RECORD
