Metadata-Version: 2.1
Name: auto-round
Version: 0.11
Summary: Repository of AutoRound: Advanced Weight-Only Quantization Algorithm for LLMs
Home-page: https://github.com/intel/auto-round
Author: Intel AIPT Team
Author-email: wenhua.cheng@intel.com, weiwei1.zhang@intel.com
License: Apache 2.0
Keywords: quantization,auto-around,LLM,SignRound
Platform: UNKNOWN
Classifier: Intended Audience :: Science/Research
Classifier: Programming Language :: Python :: 3
Classifier: Topic :: Scientific/Engineering :: Artificial Intelligence
Classifier: License :: OSI Approved :: Apache Software License
Requires-Python: >=3.7.0
License-File: LICENSE
License-File: third-party-programs.txt
Requires-Dist: accelerate
Requires-Dist: auto-gptq
Requires-Dist: datasets
Requires-Dist: py-cpuinfo
Requires-Dist: sentencepiece
Requires-Dist: torch
Requires-Dist: transformers
